flask_uwsgi_websocket/__init__.py
flask_uwsgi_websocket/_asyncio.py
flask_uwsgi_websocket/_gevent.py
flask_uwsgi_websocket/_uwsgi.py
flask_uwsgi_websocket/async.py
flask_uwsgi_websocket/websocket.py
Flask_uWSGI_Sockets-1.0.dist-info/LICENSE
Flask_uWSGI_Sockets-1.0.dist-info/METADATA
Flask_uWSGI_Sockets-1.0.dist-info/WHEEL
Flask_uWSGI_Sockets-1.0.dist-info/top_level.txt
Flask_uWSGI_Sockets-1.0.dist-info/RECORD
