Metadata-Version: 2.1
Name: Flask-uWSGI-Sockets
Version: 1.0
Summary: High-performance WebSockets for your Flask apps powered by uWSGI.
Home-page: https://github.com/level09/flask_uwsgi_websocket
Author: Nidal
Author-email: level09@gmail.com
License: MIT
Keywords: uwsgi flask websockets
Platform: any
Classifier: Environment :: Web Environment
Classifier: Intended Audience :: Developers
Classifier: License :: OSI Approved :: MIT License
Classifier: Operating System :: OS Independent
Classifier: Programming Language :: Python
Classifier: Topic :: Internet :: WWW/HTTP :: Dynamic Content
Classifier: Topic :: Software Development :: Libraries :: Python Modules
License-File: LICENSE
Requires-Dist: Flask
Requires-Dist: uwsgi
